sympy_measurement.py
sympy_measurement-0.0.1.dist-info/METADATA
sympy_measurement-0.0.1.dist-info/WHEEL
sympy_measurement-0.0.1.dist-info/top_level.txt
sympy_measurement-0.0.1.dist-info/RECORD
