Metadata-Version: 2.4
Name: sympy-measurement
Version: 0.0.1
Summary: A sympy addon for measurement value and uncertainty processing
Author-email: XeF2 <xef2@mail.ustc.edu.cn>
Classifier: Development Status :: 4 - Beta
Classifier: Programming Language :: Python :: 3
Classifier: License :: OSI Approved :: MIT License
Classifier: Operating System :: OS Independent
Classifier: Topic :: Scientific/Engineering :: Physics
Requires-Python: >=3.6
Requires-Dist: sympy>=1.11
